{
  "version": 4,
  "generated_at": "2026-04-16",
  "rationale": "Phase C C3 (2026-04-16): compute_* / save_daily_factors 全部搬家到 backend/app/services/factor_compute_service.py. 关键: compute_batch_factors 内部原 INSERT INTO factor_values + conn.commit() 改走 DataPipeline.ingest(df, FACTOR_VALUES), **F86 最后一条 factor_engine known_debt 关闭**. __init__.py 从 845 → 416 行. 剩余 2 条已知债务: fetch_base_data.py 的 klines_daily + daily_basic 拉取路径, 独立 PR 处理. 新增违规必须阻断 commit.",
  "long_term_closure_plan": {
    "fetch_base_data": "F86 剩余部分: 重构 fetch_base_data.py 走 DataPipeline(conn).ingest(df, KLINES_DAILY/DAILY_BASIC). 独立 PR."
  },
  "known_debt": [
    {
      "file": "backend/app/data_fetcher/fetch_base_data.py",
      "line_at_baseline": 327,
      "code_prefix": "INSERT INTO klines_daily",
      "ticket": "F86 long-term refactor",
      "rationale": "klines_daily 拉取路径需要迁移到 DataPipeline(conn).ingest(df, KLINES_DAILY). 独立 PR 处理.",
      "owner": "TBD",
      "deadline": "TBD"
    },
    {
      "file": "backend/app/data_fetcher/fetch_base_data.py",
      "line_at_baseline": 412,
      "code_prefix": "INSERT INTO daily_basic",
      "ticket": "F86 long-term refactor",
      "rationale": "daily_basic 拉取路径需要迁移到 DataPipeline(conn).ingest(df, DAILY_BASIC). 独立 PR 处理.",
      "owner": "TBD",
      "deadline": "TBD"
    }
  ]
}
