[
  {
    "month_end":"2014-01-31",
    "factor_rolling_ic":0.0204714962,
    "smb_momentum":-0.0025727299,
    "market_breadth":0.4139100933,
    "factor_corr_mean":0.342696632,
    "vol_regime":0.1689642526
  },
  {
    "month_end":"2014-02-28",
    "factor_rolling_ic":0.1047907426,
    "smb_momentum":0.0121537537,
    "market_breadth":0.4987179487,
    "factor_corr_mean":0.2556709145,
    "vol_regime":0.1925350189
  },
  {
    "month_end":"2014-03-31",
    "factor_rolling_ic":0.1242405911,
    "smb_momentum":0.0155845272,
    "market_breadth":0.2537562604,
    "factor_corr_mean":0.2340773008,
    "vol_regime":0.2010531861
  },
  {
    "month_end":"2014-04-30",
    "factor_rolling_ic":0.1415275387,
    "smb_momentum":0.0164715734,
    "market_breadth":0.2834943301,
    "factor_corr_mean":0.2203616175,
    "vol_regime":0.163945176
  },
  {
    "month_end":"2014-05-31",
    "factor_rolling_ic":0.08000453,
    "smb_momentum":0.0087494844,
    "market_breadth":0.5644748079,
    "factor_corr_mean":0.2906559264,
    "vol_regime":0.1282598038
  },
  {
    "month_end":"2014-06-30",
    "factor_rolling_ic":0.0631890762,
    "smb_momentum":0.0221018655,
    "market_breadth":0.7108843537,
    "factor_corr_mean":0.3198856756,
    "vol_regime":0.12140761
  },
  {
    "month_end":"2014-07-31",
    "factor_rolling_ic":0.0790235284,
    "smb_momentum":0.0120798633,
    "market_breadth":0.7845303867,
    "factor_corr_mean":0.2052129619,
    "vol_regime":0.1462413009
  },
  {
    "month_end":"2014-08-31",
    "factor_rolling_ic":0.1134822087,
    "smb_momentum":0.0263147558,
    "market_breadth":0.7983014862,
    "factor_corr_mean":0.24585361,
    "vol_regime":0.1392920616
  },
  {
    "month_end":"2014-09-30",
    "factor_rolling_ic":0.1141631453,
    "smb_momentum":0.0597066087,
    "market_breadth":0.8985324948,
    "factor_corr_mean":0.2371016108,
    "vol_regime":0.1459510305
  },
  {
    "month_end":"2014-10-31",
    "factor_rolling_ic":0.1027749202,
    "smb_momentum":0.060302231,
    "market_breadth":0.4096334186,
    "factor_corr_mean":0.2088490529,
    "vol_regime":0.1400244513
  },
  {
    "month_end":"2014-11-30",
    "factor_rolling_ic":0.0762973124,
    "smb_momentum":0.0160266264,
    "market_breadth":0.6323841904,
    "factor_corr_mean":0.2299442855,
    "vol_regime":0.1705294094
  },
  {
    "month_end":"2014-12-31",
    "factor_rolling_ic":0.0634584083,
    "smb_momentum":-0.174784261,
    "market_breadth":0.343083995,
    "factor_corr_mean":0.1747821193,
    "vol_regime":0.3731640359
  },
  {
    "month_end":"2015-01-31",
    "factor_rolling_ic":0.0521484137,
    "smb_momentum":-0.1570988492,
    "market_breadth":0.7253254935,
    "factor_corr_mean":0.1998506694,
    "vol_regime":0.3813051797
  },
  {
    "month_end":"2015-02-28",
    "factor_rolling_ic":0.0556323464,
    "smb_momentum":-0.1403518185,
    "market_breadth":0.9041966935,
    "factor_corr_mean":0.2483367002,
    "vol_regime":0.2218364158
  },
  {
    "month_end":"2015-03-31",
    "factor_rolling_ic":0.0587369972,
    "smb_momentum":0.0087068691,
    "market_breadth":0.9623500207,
    "factor_corr_mean":0.2511901943,
    "vol_regime":0.1908283132
  },
  {
    "month_end":"2015-04-30",
    "factor_rolling_ic":0.0515298414,
    "smb_momentum":-0.0080784554,
    "market_breadth":0.8363412633,
    "factor_corr_mean":0.2395589861,
    "vol_regime":0.2276327085
  },
  {
    "month_end":"2015-05-31",
    "factor_rolling_ic":0.0750671317,
    "smb_momentum":0.0659373012,
    "market_breadth":0.8702479339,
    "factor_corr_mean":0.2974567977,
    "vol_regime":0.3875274599
  },
  {
    "month_end":"2015-06-30",
    "factor_rolling_ic":0.0847483991,
    "smb_momentum":0.0332941881,
    "market_breadth":0.1685950413,
    "factor_corr_mean":0.1547165688,
    "vol_regime":0.5274143605
  },
  {
    "month_end":"2015-07-31",
    "factor_rolling_ic":0.0946770418,
    "smb_momentum":-0.0087054364,
    "market_breadth":0.1755341433,
    "factor_corr_mean":0.1466449756,
    "vol_regime":0.5853820385
  },
  {
    "month_end":"2015-08-31",
    "factor_rolling_ic":0.0945051097,
    "smb_momentum":-0.0798530259,
    "market_breadth":0.1650607457,
    "factor_corr_mean":0.1700941101,
    "vol_regime":0.6102753001
  },
  {
    "month_end":"2015-09-30",
    "factor_rolling_ic":0.0522033671,
    "smb_momentum":-0.0465193209,
    "market_breadth":0.6033472803,
    "factor_corr_mean":0.1952187616,
    "vol_regime":0.3373858865
  },
  {
    "month_end":"2015-10-31",
    "factor_rolling_ic":0.0333378192,
    "smb_momentum":0.0389851808,
    "market_breadth":0.933908046,
    "factor_corr_mean":0.2255496709,
    "vol_regime":0.2472511722
  },
  {
    "month_end":"2015-11-30",
    "factor_rolling_ic":0.0280325363,
    "smb_momentum":0.1012726178,
    "market_breadth":0.7787963332,
    "factor_corr_mean":0.3150473565,
    "vol_regime":0.3009448109
  },
  {
    "month_end":"2015-12-31",
    "factor_rolling_ic":0.0867241891,
    "smb_momentum":0.1262294529,
    "market_breadth":0.6745815492,
    "factor_corr_mean":0.2264774203,
    "vol_regime":0.2188508835
  },
  {
    "month_end":"2016-01-31",
    "factor_rolling_ic":0.111926126,
    "smb_momentum":0.0384402568,
    "market_breadth":0.0307273434,
    "factor_corr_mean":0.2000961764,
    "vol_regime":0.5042465934
  },
  {
    "month_end":"2016-02-29",
    "factor_rolling_ic":0.1259316267,
    "smb_momentum":-0.0277218091,
    "market_breadth":0.3656745265,
    "factor_corr_mean":0.2009055203,
    "vol_regime":0.3936260767
  },
  {
    "month_end":"2016-03-31",
    "factor_rolling_ic":0.093853363,
    "smb_momentum":-0.0434304182,
    "market_breadth":0.9412893323,
    "factor_corr_mean":0.2660290904,
    "vol_regime":0.1954097553
  },
  {
    "month_end":"2016-04-30",
    "factor_rolling_ic":0.1012038078,
    "smb_momentum":0.0411792477,
    "market_breadth":0.3993055556,
    "factor_corr_mean":0.2173669625,
    "vol_regime":0.1375182283
  },
  {
    "month_end":"2016-05-31",
    "factor_rolling_ic":0.0522697553,
    "smb_momentum":0.0114844438,
    "market_breadth":0.238428627,
    "factor_corr_mean":0.2404877648,
    "vol_regime":0.177954288
  },
  {
    "month_end":"2016-06-30",
    "factor_rolling_ic":0.0763911111,
    "smb_momentum":0.0037143568,
    "market_breadth":0.6979166667,
    "factor_corr_mean":0.3103368399,
    "vol_regime":0.153049339
  },
  {
    "month_end":"2016-07-31",
    "factor_rolling_ic":0.1035880371,
    "smb_momentum":-0.0548658068,
    "market_breadth":0.4388297872,
    "factor_corr_mean":0.2058688061,
    "vol_regime":0.1316196972
  },
  {
    "month_end":"2016-08-31",
    "factor_rolling_ic":0.1548424925,
    "smb_momentum":-0.0075588995,
    "market_breadth":0.8607975922,
    "factor_corr_mean":0.2419852673,
    "vol_regime":0.1396086096
  },
  {
    "month_end":"2016-09-30",
    "factor_rolling_ic":0.1324714258,
    "smb_momentum":0.0003365604,
    "market_breadth":0.3977653631,
    "factor_corr_mean":0.2324778101,
    "vol_regime":0.1118784637
  },
  {
    "month_end":"2016-10-31",
    "factor_rolling_ic":0.0963970614,
    "smb_momentum":0.036896619,
    "market_breadth":0.5393424455,
    "factor_corr_mean":0.2432033596,
    "vol_regime":0.0887585541
  },
  {
    "month_end":"2016-11-30",
    "factor_rolling_ic":0.0979363691,
    "smb_momentum":0.0302206343,
    "market_breadth":0.5474028333,
    "factor_corr_mean":0.2430789547,
    "vol_regime":0.0847332643
  },
  {
    "month_end":"2016-12-31",
    "factor_rolling_ic":0.1141275275,
    "smb_momentum":0.0088295533,
    "market_breadth":0.1931531532,
    "factor_corr_mean":0.1778670727,
    "vol_regime":0.1248334215
  },
  {
    "month_end":"2017-01-31",
    "factor_rolling_ic":0.1058117099,
    "smb_momentum":-0.0341527713,
    "market_breadth":0.2611967037,
    "factor_corr_mean":0.2213256586,
    "vol_regime":0.0712276059
  },
  {
    "month_end":"2017-02-28",
    "factor_rolling_ic":0.0724868449,
    "smb_momentum":-0.0416736961,
    "market_breadth":0.8186968839,
    "factor_corr_mean":0.2572501815,
    "vol_regime":0.0847642882
  },
  {
    "month_end":"2017-03-31",
    "factor_rolling_ic":0.0607195535,
    "smb_momentum":-0.0682254358,
    "market_breadth":0.2948096886,
    "factor_corr_mean":0.2538175358,
    "vol_regime":0.0822019384
  },
  {
    "month_end":"2017-04-30",
    "factor_rolling_ic":0.0481442147,
    "smb_momentum":-0.1027594854,
    "market_breadth":0.1413415469,
    "factor_corr_mean":0.1978629904,
    "vol_regime":0.0867586707
  },
  {
    "month_end":"2017-05-31",
    "factor_rolling_ic":0.0478256938,
    "smb_momentum":-0.1429936808,
    "market_breadth":0.1695088677,
    "factor_corr_mean":0.2124214628,
    "vol_regime":0.0972399248
  },
  {
    "month_end":"2017-06-30",
    "factor_rolling_ic":0.0549410481,
    "smb_momentum":-0.1392686419,
    "market_breadth":0.8595069233,
    "factor_corr_mean":0.2298961373,
    "vol_regime":0.1091540162
  },
  {
    "month_end":"2017-07-31",
    "factor_rolling_ic":0.079574143,
    "smb_momentum":-0.1257500931,
    "market_breadth":0.3632436025,
    "factor_corr_mean":0.2055497059,
    "vol_regime":0.1033345629
  },
  {
    "month_end":"2017-08-31",
    "factor_rolling_ic":0.0782564026,
    "smb_momentum":-0.0713374242,
    "market_breadth":0.6918776718,
    "factor_corr_mean":0.281838994,
    "vol_regime":0.1182783336
  },
  {
    "month_end":"2017-09-30",
    "factor_rolling_ic":0.0658420817,
    "smb_momentum":-0.0521597605,
    "market_breadth":0.4405144695,
    "factor_corr_mean":0.2510802841,
    "vol_regime":0.0431985495
  },
  {
    "month_end":"2017-10-31",
    "factor_rolling_ic":0.0434269692,
    "smb_momentum":-0.0208413634,
    "market_breadth":0.2991725016,
    "factor_corr_mean":0.243492448,
    "vol_regime":0.0618340882
  },
  {
    "month_end":"2017-11-30",
    "factor_rolling_ic":0.0678417801,
    "smb_momentum":-0.0889565198,
    "market_breadth":0.1646875,
    "factor_corr_mean":0.2162297844,
    "vol_regime":0.1590958914
  },
  {
    "month_end":"2017-12-31",
    "factor_rolling_ic":0.0530103134,
    "smb_momentum":-0.1114055982,
    "market_breadth":0.3081721772,
    "factor_corr_mean":0.2256107152,
    "vol_regime":0.1400389731
  },
  {
    "month_end":"2018-01-31",
    "factor_rolling_ic":0.0731755474,
    "smb_momentum":-0.1355586306,
    "market_breadth":0.2747456059,
    "factor_corr_mean":0.1974292788,
    "vol_regime":0.1097029317
  },
  {
    "month_end":"2018-02-28",
    "factor_rolling_ic":0.0303724082,
    "smb_momentum":-0.1177121482,
    "market_breadth":0.4088943792,
    "factor_corr_mean":0.2225245757,
    "vol_regime":0.249490016
  },
  {
    "month_end":"2018-03-31",
    "factor_rolling_ic":0.0289358727,
    "smb_momentum":-0.0432459136,
    "market_breadth":0.6015479876,
    "factor_corr_mean":0.3008088097,
    "vol_regime":0.165966304
  },
  {
    "month_end":"2018-04-30",
    "factor_rolling_ic":0.0112676604,
    "smb_momentum":-0.013048904,
    "market_breadth":0.2333538841,
    "factor_corr_mean":0.2551485975,
    "vol_regime":0.1755160925
  },
  {
    "month_end":"2018-05-31",
    "factor_rolling_ic":0.0155689034,
    "smb_momentum":0.0186856868,
    "market_breadth":0.4197869102,
    "factor_corr_mean":0.2899492326,
    "vol_regime":0.1617451275
  },
  {
    "month_end":"2018-06-30",
    "factor_rolling_ic":0.0242747077,
    "smb_momentum":-0.0583723433,
    "market_breadth":0.1180744777,
    "factor_corr_mean":0.2619944684,
    "vol_regime":0.204982244
  },
  {
    "month_end":"2018-07-31",
    "factor_rolling_ic":0.0811770612,
    "smb_momentum":-0.0465122554,
    "market_breadth":0.6016872552,
    "factor_corr_mean":0.2833629013,
    "vol_regime":0.1873205661
  },
  {
    "month_end":"2018-08-31",
    "factor_rolling_ic":0.1083317805,
    "smb_momentum":-0.0592297141,
    "market_breadth":0.1516052319,
    "factor_corr_mean":0.2432402454,
    "vol_regime":0.2271126037
  },
  {
    "month_end":"2018-09-30",
    "factor_rolling_ic":0.1036338349,
    "smb_momentum":-0.0384538072,
    "market_breadth":0.4550810015,
    "factor_corr_mean":0.2270017402,
    "vol_regime":0.1968082487
  },
  {
    "month_end":"2018-10-31",
    "factor_rolling_ic":0.078673394,
    "smb_momentum":-0.0224036921,
    "market_breadth":0.1841566793,
    "factor_corr_mean":0.2500429674,
    "vol_regime":0.3551383684
  },
  {
    "month_end":"2018-11-30",
    "factor_rolling_ic":0.0875496616,
    "smb_momentum":0.013868458,
    "market_breadth":0.711888921,
    "factor_corr_mean":0.2199427626,
    "vol_regime":0.1769772573
  },
  {
    "month_end":"2018-12-31",
    "factor_rolling_ic":0.1122843861,
    "smb_momentum":0.0203223203,
    "market_breadth":0.130008648,
    "factor_corr_mean":0.2421181407,
    "vol_regime":0.17669344
  },
  {
    "month_end":"2019-01-31",
    "factor_rolling_ic":0.0859589422,
    "smb_momentum":-0.0451445575,
    "market_breadth":0.3952819333,
    "factor_corr_mean":0.1925613914,
    "vol_regime":0.1513047221
  },
  {
    "month_end":"2019-02-28",
    "factor_rolling_ic":0.0662043493,
    "smb_momentum":-0.0529479106,
    "market_breadth":0.9887931034,
    "factor_corr_mean":0.2057476485,
    "vol_regime":0.2696548718
  },
  {
    "month_end":"2019-03-31",
    "factor_rolling_ic":0.0723534811,
    "smb_momentum":-0.0662192812,
    "market_breadth":0.852074392,
    "factor_corr_mean":0.219967501,
    "vol_regime":0.2715950799
  },
  {
    "month_end":"2019-04-30",
    "factor_rolling_ic":0.1018915878,
    "smb_momentum":-0.0412923642,
    "market_breadth":0.1741733181,
    "factor_corr_mean":0.1941881608,
    "vol_regime":0.1932550028
  },
  {
    "month_end":"2019-05-31",
    "factor_rolling_ic":0.1141772769,
    "smb_momentum":-0.0373330289,
    "market_breadth":0.6138528139,
    "factor_corr_mean":0.2477781808,
    "vol_regime":0.3104595284
  },
  {
    "month_end":"2019-06-30",
    "factor_rolling_ic":0.1098456698,
    "smb_momentum":-0.0386866355,
    "market_breadth":0.6216839677,
    "factor_corr_mean":0.2324071107,
    "vol_regime":0.1822902362
  },
  {
    "month_end":"2019-07-31",
    "factor_rolling_ic":0.0698688081,
    "smb_momentum":-0.030924081,
    "market_breadth":0.2195402299,
    "factor_corr_mean":0.2277769196,
    "vol_regime":0.1217934961
  },
  {
    "month_end":"2019-08-31",
    "factor_rolling_ic":0.050456961,
    "smb_momentum":-0.0689959967,
    "market_breadth":0.339162844,
    "factor_corr_mean":0.2806739031,
    "vol_regime":0.1670080337
  },
  {
    "month_end":"2019-09-30",
    "factor_rolling_ic":0.0460288182,
    "smb_momentum":-0.0543810243,
    "market_breadth":0.3457280727,
    "factor_corr_mean":0.2665323723,
    "vol_regime":0.1291172893
  },
  {
    "month_end":"2019-10-31",
    "factor_rolling_ic":0.0524041376,
    "smb_momentum":-0.0487628952,
    "market_breadth":0.393220339,
    "factor_corr_mean":0.2310281273,
    "vol_regime":0.1046722958
  },
  {
    "month_end":"2019-11-30",
    "factor_rolling_ic":0.0659559647,
    "smb_momentum":-0.0428614316,
    "market_breadth":0.2383098592,
    "factor_corr_mean":0.2499657021,
    "vol_regime":0.1135178083
  },
  {
    "month_end":"2019-12-31",
    "factor_rolling_ic":0.0431608347,
    "smb_momentum":-0.0499373789,
    "market_breadth":0.893718452,
    "factor_corr_mean":0.2682711721,
    "vol_regime":0.115520131
  },
  {
    "month_end":"2020-01-31",
    "factor_rolling_ic":0.0228530415,
    "smb_momentum":-0.0690715487,
    "market_breadth":0.3089793642,
    "factor_corr_mean":null,
    "vol_regime":0.173546257
  },
  {
    "month_end":"2020-02-29",
    "factor_rolling_ic":0.0529955041,
    "smb_momentum":-0.0996677087,
    "market_breadth":0.8076923077,
    "factor_corr_mean":0.2720056591,
    "vol_regime":0.3607574586
  },
  {
    "month_end":"2020-03-31",
    "factor_rolling_ic":0.0726912824,
    "smb_momentum":-0.0644506981,
    "market_breadth":0.1853483889,
    "factor_corr_mean":0.2255181723,
    "vol_regime":0.3235048031
  },
  {
    "month_end":"2020-04-30",
    "factor_rolling_ic":0.0890014028,
    "smb_momentum":-0.089883479,
    "market_breadth":0.5737346101,
    "factor_corr_mean":0.2661825339,
    "vol_regime":0.1512175206
  },
  {
    "month_end":"2020-05-31",
    "factor_rolling_ic":0.0451840038,
    "smb_momentum":-0.0503707984,
    "market_breadth":0.4227033028,
    "factor_corr_mean":0.2802549342,
    "vol_regime":0.1287764846
  },
  {
    "month_end":"2020-06-30",
    "factor_rolling_ic":0.0179735338,
    "smb_momentum":-0.1209634915,
    "market_breadth":0.5711527854,
    "factor_corr_mean":0.2905623739,
    "vol_regime":0.1402633883
  },
  {
    "month_end":"2020-07-31",
    "factor_rolling_ic":0.0425175132,
    "smb_momentum":-0.0898065492,
    "market_breadth":0.8488275862,
    "factor_corr_mean":0.2478300688,
    "vol_regime":0.3672239028
  },
  {
    "month_end":"2020-08-31",
    "factor_rolling_ic":0.0711891613,
    "smb_momentum":-0.0701143535,
    "market_breadth":0.44614963,
    "factor_corr_mean":0.2215747912,
    "vol_regime":0.1742311248
  },
  {
    "month_end":"2020-09-30",
    "factor_rolling_ic":0.0560345587,
    "smb_momentum":-0.0375716096,
    "market_breadth":0.1403033586,
    "factor_corr_mean":0.2326351383,
    "vol_regime":0.1757466024
  },
  {
    "month_end":"2020-10-31",
    "factor_rolling_ic":0.0690105118,
    "smb_momentum":-0.0030811978,
    "market_breadth":0.2770955686,
    "factor_corr_mean":0.2804363752,
    "vol_regime":0.1633213573
  },
  {
    "month_end":"2020-11-30",
    "factor_rolling_ic":0.077908587,
    "smb_momentum":-0.032305798,
    "market_breadth":0.6208704772,
    "factor_corr_mean":0.2423190122,
    "vol_regime":0.143937269
  },
  {
    "month_end":"2020-12-31",
    "factor_rolling_ic":0.1086089562,
    "smb_momentum":-0.1076805446,
    "market_breadth":0.2436164669,
    "factor_corr_mean":0.2366519066,
    "vol_regime":0.147244959
  },
  {
    "month_end":"2021-01-31",
    "factor_rolling_ic":0.0960684609,
    "smb_momentum":-0.1936856843,
    "market_breadth":0.1876133713,
    "factor_corr_mean":0.2352802105,
    "vol_regime":0.2288886719
  },
  {
    "month_end":"2021-02-28",
    "factor_rolling_ic":0.0927364144,
    "smb_momentum":-0.1588503082,
    "market_breadth":0.6482193185,
    "factor_corr_mean":0.2103200147,
    "vol_regime":0.2552565469
  },
  {
    "month_end":"2021-03-31",
    "factor_rolling_ic":0.1006856473,
    "smb_momentum":-0.0570750313,
    "market_breadth":0.4154822335,
    "factor_corr_mean":0.2180221371,
    "vol_regime":0.2661333319
  },
  {
    "month_end":"2021-04-30",
    "factor_rolling_ic":0.0851835442,
    "smb_momentum":-0.0211276517,
    "market_breadth":0.434256927,
    "factor_corr_mean":0.2233606425,
    "vol_regime":0.1526738057
  },
  {
    "month_end":"2021-05-31",
    "factor_rolling_ic":0.0498514866,
    "smb_momentum":-0.046623621,
    "market_breadth":0.7235875348,
    "factor_corr_mean":0.2839233375,
    "vol_regime":0.1774379054
  },
  {
    "month_end":"2021-06-30",
    "factor_rolling_ic":0.0296140026,
    "smb_momentum":-0.0788027309,
    "market_breadth":0.471367842,
    "factor_corr_mean":0.2744864692,
    "vol_regime":0.1280924427
  },
  {
    "month_end":"2021-07-31",
    "factor_rolling_ic":0.0300016524,
    "smb_momentum":-0.0646747951,
    "market_breadth":0.4089108911,
    "factor_corr_mean":0.2891107626,
    "vol_regime":0.2156234431
  },
  {
    "month_end":"2021-08-31",
    "factor_rolling_ic":0.0653496635,
    "smb_momentum":-0.0725307258,
    "market_breadth":0.5948655257,
    "factor_corr_mean":0.2496356126,
    "vol_regime":0.1711228341
  },
  {
    "month_end":"2021-09-30",
    "factor_rolling_ic":0.0852081327,
    "smb_momentum":-0.079035562,
    "market_breadth":0.330510525,
    "factor_corr_mean":0.2162390226,
    "vol_regime":0.1458772969
  },
  {
    "month_end":"2021-10-31",
    "factor_rolling_ic":0.0792840658,
    "smb_momentum":-0.082139288,
    "market_breadth":0.2669704965,
    "factor_corr_mean":0.2629774756,
    "vol_regime":0.1272052203
  },
  {
    "month_end":"2021-11-30",
    "factor_rolling_ic":0.0781550889,
    "smb_momentum":-0.033385386,
    "market_breadth":0.7593252554,
    "factor_corr_mean":0.2924628869,
    "vol_regime":0.0989619924
  },
  {
    "month_end":"2021-12-31",
    "factor_rolling_ic":0.1127238925,
    "smb_momentum":-0.0047588544,
    "market_breadth":0.5517322649,
    "factor_corr_mean":0.2206342305,
    "vol_regime":0.1472958437
  },
  {
    "month_end":"2022-01-31",
    "factor_rolling_ic":0.1292248419,
    "smb_momentum":0.0459303665,
    "market_breadth":0.0982915984,
    "factor_corr_mean":0.2194816,
    "vol_regime":0.1600126063
  },
  {
    "month_end":"2022-02-28",
    "factor_rolling_ic":0.0847200587,
    "smb_momentum":0.0090225866,
    "market_breadth":0.6340050961,
    "factor_corr_mean":0.2535824512,
    "vol_regime":0.1797483562
  },
  {
    "month_end":"2022-03-31",
    "factor_rolling_ic":0.0618870541,
    "smb_momentum":0.0227211215,
    "market_breadth":0.2376351507,
    "factor_corr_mean":0.2492363008,
    "vol_regime":0.3270060371
  },
  {
    "month_end":"2022-04-30",
    "factor_rolling_ic":0.0506547593,
    "smb_momentum":-0.0678651324,
    "market_breadth":0.088262265,
    "factor_corr_mean":0.2413973467,
    "vol_regime":0.2898713737
  },
  {
    "month_end":"2022-05-31",
    "factor_rolling_ic":0.0703144182,
    "smb_momentum":-0.0530473066,
    "market_breadth":0.8620372499,
    "factor_corr_mean":0.2608884947,
    "vol_regime":0.2006411013
  },
  {
    "month_end":"2022-06-30",
    "factor_rolling_ic":0.0513822183,
    "smb_momentum":-0.1012616967,
    "market_breadth":0.7697398448,
    "factor_corr_mean":0.2764814224,
    "vol_regime":0.170052104
  },
  {
    "month_end":"2022-07-31",
    "factor_rolling_ic":0.0634521505,
    "smb_momentum":-0.0035496389,
    "market_breadth":0.5418562329,
    "factor_corr_mean":0.2763620938,
    "vol_regime":0.1286657875
  },
  {
    "month_end":"2022-08-31",
    "factor_rolling_ic":0.0828389618,
    "smb_momentum":-0.0260957707,
    "market_breadth":0.2974440172,
    "factor_corr_mean":0.2167479054,
    "vol_regime":0.1415355156
  },
  {
    "month_end":"2022-09-30",
    "factor_rolling_ic":0.0898911016,
    "smb_momentum":-0.0173306129,
    "market_breadth":0.1230042725,
    "factor_corr_mean":0.2421315718,
    "vol_regime":0.1437214408
  },
  {
    "month_end":"2022-10-31",
    "factor_rolling_ic":0.0864968476,
    "smb_momentum":-0.0208255924,
    "market_breadth":0.6606546426,
    "factor_corr_mean":0.2387155396,
    "vol_regime":0.211109979
  },
  {
    "month_end":"2022-11-30",
    "factor_rolling_ic":0.0815843557,
    "smb_momentum":-0.0155904465,
    "market_breadth":0.6748290315,
    "factor_corr_mean":0.2373973564,
    "vol_regime":0.2167601596
  },
  {
    "month_end":"2022-12-31",
    "factor_rolling_ic":0.0766535768,
    "smb_momentum":-0.0133587661,
    "market_breadth":0.1935908692,
    "factor_corr_mean":0.2384881988,
    "vol_regime":0.1324413521
  },
  {
    "month_end":"2023-01-31",
    "factor_rolling_ic":0.1038353354,
    "smb_momentum":-0.0310334246,
    "market_breadth":0.820602357,
    "factor_corr_mean":0.2590815909,
    "vol_regime":0.1135407473
  },
  {
    "month_end":"2023-02-28",
    "factor_rolling_ic":0.1202079563,
    "smb_momentum":-0.007096128,
    "market_breadth":0.5587149989,
    "factor_corr_mean":0.2331238686,
    "vol_regime":0.1524666027
  },
  {
    "month_end":"2023-03-31",
    "factor_rolling_ic":0.1096751901,
    "smb_momentum":-0.0054180997,
    "market_breadth":0.3081761006,
    "factor_corr_mean":0.2243076926,
    "vol_regime":0.1192786844
  },
  {
    "month_end":"2023-04-30",
    "factor_rolling_ic":0.0900591673,
    "smb_momentum":-0.0533682285,
    "market_breadth":0.2773454388,
    "factor_corr_mean":0.2041189259,
    "vol_regime":0.1279966728
  },
  {
    "month_end":"2023-05-31",
    "factor_rolling_ic":0.0368264076,
    "smb_momentum":-0.034885565,
    "market_breadth":0.4505757115,
    "factor_corr_mean":0.2189493089,
    "vol_regime":0.121010933
  },
  {
    "month_end":"2023-06-30",
    "factor_rolling_ic":0.0664557087,
    "smb_momentum":-0.0071605124,
    "market_breadth":0.5607860073,
    "factor_corr_mean":0.2844906759,
    "vol_regime":0.1363875262
  },
  {
    "month_end":"2023-07-31",
    "factor_rolling_ic":0.0779188984,
    "smb_momentum":0.0324091184,
    "market_breadth":0.5298539519,
    "factor_corr_mean":0.2267472319,
    "vol_regime":0.1581342627
  },
  {
    "month_end":"2023-08-31",
    "factor_rolling_ic":0.1106893197,
    "smb_momentum":0.0224718627,
    "market_breadth":0.2505335041,
    "factor_corr_mean":0.2678319699,
    "vol_regime":0.1428605274
  },
  {
    "month_end":"2023-09-30",
    "factor_rolling_ic":0.0821901351,
    "smb_momentum":0.0094914033,
    "market_breadth":0.4151823579,
    "factor_corr_mean":0.2182791826,
    "vol_regime":0.1255078994
  },
  {
    "month_end":"2023-10-31",
    "factor_rolling_ic":0.0484694565,
    "smb_momentum":0.0189238865,
    "market_breadth":0.4184232715,
    "factor_corr_mean":0.2660653457,
    "vol_regime":0.1293047053
  },
  {
    "month_end":"2023-11-30",
    "factor_rolling_ic":0.0426941313,
    "smb_momentum":0.0183264179,
    "market_breadth":0.6539108495,
    "factor_corr_mean":0.2540594894,
    "vol_regime":0.0998837739
  },
  {
    "month_end":"2023-12-31",
    "factor_rolling_ic":0.0614568951,
    "smb_momentum":0.0202105119,
    "market_breadth":0.253621667,
    "factor_corr_mean":0.2480260705,
    "vol_regime":0.1453767921
  },
  {
    "month_end":"2024-01-31",
    "factor_rolling_ic":0.0558653982,
    "smb_momentum":-0.0593289393,
    "market_breadth":0.0624345276,
    "factor_corr_mean":0.1871775362,
    "vol_regime":0.171666246
  },
  {
    "month_end":"2024-02-29",
    "factor_rolling_ic":0.0344432742,
    "smb_momentum":-0.174888916,
    "market_breadth":0.7799832846,
    "factor_corr_mean":0.1989418082,
    "vol_regime":0.2068512605
  },
  {
    "month_end":"2024-03-31",
    "factor_rolling_ic":0.0557824454,
    "smb_momentum":-0.123925683,
    "market_breadth":0.5867751356,
    "factor_corr_mean":0.2553857351,
    "vol_regime":0.1031959761
  },
  {
    "month_end":"2024-04-30",
    "factor_rolling_ic":0.0740083745,
    "smb_momentum":-0.1069468155,
    "market_breadth":0.3142321317,
    "factor_corr_mean":0.1574909096,
    "vol_regime":0.1529300951
  },
  {
    "month_end":"2024-05-31",
    "factor_rolling_ic":0.0745524666,
    "smb_momentum":-0.0151762211,
    "market_breadth":0.2534766119,
    "factor_corr_mean":0.2296202628,
    "vol_regime":0.1160174173
  },
  {
    "month_end":"2024-06-30",
    "factor_rolling_ic":0.0456618014,
    "smb_momentum":-0.0890830181,
    "market_breadth":0.1484605652,
    "factor_corr_mean":0.2137401067,
    "vol_regime":0.0751377671
  },
  {
    "month_end":"2024-07-31",
    "factor_rolling_ic":0.0537978141,
    "smb_momentum":-0.0349072924,
    "market_breadth":0.4377239199,
    "factor_corr_mean":0.2311474724,
    "vol_regime":0.1432658582
  },
  {
    "month_end":"2024-08-31",
    "factor_rolling_ic":0.0723349565,
    "smb_momentum":-0.0233910822,
    "market_breadth":0.2381454162,
    "factor_corr_mean":0.2339185677,
    "vol_regime":0.0919061694
  },
  {
    "month_end":"2024-09-30",
    "factor_rolling_ic":0.0288680845,
    "smb_momentum":-0.0135083693,
    "market_breadth":0.9947368421,
    "factor_corr_mean":0.261717834,
    "vol_regime":0.3880235948
  },
  {
    "month_end":"2024-10-31",
    "factor_rolling_ic":0.0220414541,
    "smb_momentum":-0.0094847907,
    "market_breadth":0.2843322818,
    "factor_corr_mean":0.3149055494,
    "vol_regime":0.5190540843
  },
  {
    "month_end":"2024-11-30",
    "factor_rolling_ic":0.0432131896,
    "smb_momentum":-0.0061718265,
    "market_breadth":0.7469019114,
    "factor_corr_mean":0.2776161706,
    "vol_regime":0.2335668674
  },
  {
    "month_end":"2024-12-31",
    "factor_rolling_ic":0.0964140789,
    "smb_momentum":-0.0377779797,
    "market_breadth":0.2047838859,
    "factor_corr_mean":0.2076949595,
    "vol_regime":0.1365957389
  },
  {
    "month_end":"2025-01-31",
    "factor_rolling_ic":0.0806546643,
    "smb_momentum":-0.0418183006,
    "market_breadth":0.4819630872,
    "factor_corr_mean":0.2285533992,
    "vol_regime":0.1734191669
  },
  {
    "month_end":"2025-02-28",
    "factor_rolling_ic":0.0688153481,
    "smb_momentum":-0.0586018597,
    "market_breadth":0.7227805695,
    "factor_corr_mean":0.2906448726,
    "vol_regime":0.1390839125
  },
  {
    "month_end":"2025-03-31",
    "factor_rolling_ic":0.0802585118,
    "smb_momentum":-0.0224605002,
    "market_breadth":0.4244514107,
    "factor_corr_mean":0.1892839728,
    "vol_regime":0.1293290364
  },
  {
    "month_end":"2025-04-30",
    "factor_rolling_ic":0.0927169105,
    "smb_momentum":-0.0154697595,
    "market_breadth":0.277638191,
    "factor_corr_mean":0.2139351081,
    "vol_regime":0.2675240166
  },
  {
    "month_end":"2025-05-31",
    "factor_rolling_ic":0.0938177103,
    "smb_momentum":0.0166195977,
    "market_breadth":0.5500529101,
    "factor_corr_mean":0.2847027864,
    "vol_regime":0.1006853396
  },
  {
    "month_end":"2025-06-30",
    "factor_rolling_ic":0.0888835115,
    "smb_momentum":0.0315598811,
    "market_breadth":0.717001056,
    "factor_corr_mean":0.2853840509,
    "vol_regime":0.0909943085
  },
  {
    "month_end":"2025-07-31",
    "factor_rolling_ic":0.0819199173,
    "smb_momentum":0.013054808,
    "market_breadth":0.6895969614,
    "factor_corr_mean":0.2300148107,
    "vol_regime":0.0963884995
  },
  {
    "month_end":"2025-08-31",
    "factor_rolling_ic":0.0682104188,
    "smb_momentum":-0.0738281583,
    "market_breadth":0.7251054852,
    "factor_corr_mean":0.2791900528,
    "vol_regime":0.1349599476
  },
  {
    "month_end":"2025-09-30",
    "factor_rolling_ic":0.0659617208,
    "smb_momentum":-0.113408101,
    "market_breadth":0.363540569,
    "factor_corr_mean":0.2437915396,
    "vol_regime":0.1691569906
  },
  {
    "month_end":"2025-10-31",
    "factor_rolling_ic":0.087921275,
    "smb_momentum":-0.0856468996,
    "market_breadth":0.4887154609,
    "factor_corr_mean":0.2257801099,
    "vol_regime":0.1916550852
  },
  {
    "month_end":"2025-11-30",
    "factor_rolling_ic":0.0834963234,
    "smb_momentum":-0.0092263287,
    "market_breadth":0.3205479452,
    "factor_corr_mean":0.259742245,
    "vol_regime":0.1434509865
  },
  {
    "month_end":"2025-12-31",
    "factor_rolling_ic":0.058305021,
    "smb_momentum":-0.0299317282,
    "market_breadth":0.4286616162,
    "factor_corr_mean":0.2931749681,
    "vol_regime":0.1126549349
  },
  {
    "month_end":"2026-01-31",
    "factor_rolling_ic":0.0559817452,
    "smb_momentum":-0.0686337584,
    "market_breadth":0.6761363636,
    "factor_corr_mean":0.2481963101,
    "vol_regime":0.1129530869
  },
  {
    "month_end":"2026-02-28",
    "factor_rolling_ic":0.0616962454,
    "smb_momentum":-0.0923408147,
    "market_breadth":0.8202058391,
    "factor_corr_mean":0.2534106243,
    "vol_regime":0.1387433733
  },
  {
    "month_end":"2026-03-31",
    "factor_rolling_ic":0.0784430178,
    "smb_momentum":-0.0505406829,
    "market_breadth":0.1615271659,
    "factor_corr_mean":0.2317945839,
    "vol_regime":0.1804579194
  },
  {
    "month_end":"2026-04-30",
    "factor_rolling_ic":0.0686654036,
    "smb_momentum":-0.040983874,
    "market_breadth":0.6651270208,
    "factor_corr_mean":0.2328875423,
    "vol_regime":0.2214376298
  }
]